[
    {
        "model": "Settings.idtype",
        "pk": 1,
        "fields": {
            "description": "Cedula",
            "abbreviation": "CC"
        }
    },
    {
        "model": "Settings.idtype",
        "pk": 2,
        "fields": {
            "description": "Registro Civil",
            "abbreviation": "RC"
        }
    },
    {
        "model": "Settings.idtype",
        "pk": 3,
        "fields": {
            "description": "Pasaporte",
            "abbreviation": "PA"
        }
    },
    {
        "model": "Settings.idtype",
        "pk": 4,
        "fields": {
            "description": "Cedula Extranjeria",
            "abbreviation": "CE"
        }
    },
    {
        "model": "Settings.idtype",
        "pk": 5,
        "fields": {
            "description": "Tarjeta Identidad",
            "abbreviation": "TI"
        }
    },
    {
        "model": "Settings.idtype",
        "pk": 6,
        "fields": {
            "description": "Carnet Diplomatico",
            "abbreviation": "CD"
        }
    },
    {
        "model": "Settings.idtype",
        "pk": 7,
        "fields": {
            "description": "Numero Unico Tributario",
            "abbreviation": "NIT"
        }
    },
    {
        "model": "Settings.gender",
        "pk": 1,
        "fields": {
            "name_gender": "Femenino"
        }
    },
    {
        "model": "Settings.gender",
        "pk": 2,
        "fields": {
            "name_gender": "Masculino"
        }
    },
    {
        "model": "Settings.operationtype",
        "pk": 1,
        "fields": {
            "description": "Venta"
        }
    },
    {
        "model": "Settings.distributionproducttype",
        "pk": 1,
        "fields": {
            "description": "Unidad",
            "profit_seller": 0.45,
            "profit_bussiness": 0.45,
            "profit_operational": 0.1
        }
    },
    {
        "model": "Settings.distributionproducttype",
        "pk": 2,
        "fields": {
            "description": "Kit",
            "profit_seller": 0.38,
            "profit_bussiness": 0.52,
            "profit_operational": 0.1
        }
    },
    {
        "model": "Settings.PaymentMethod",
        "pk": 1,
        "fields": {
            "code": "EF",
            "description": "Efectivo"
        }
    },
    {
        "model": "Settings.PaymentMethod",
        "pk": 2,
        "fields": {
            "code": "CH",
            "description": "Cheque"
        }
    },
    {
        "model": "Settings.PaymentMethod",
        "pk": 3,
        "fields": {
            "code": "TB",
            "description": "Transaccion Bancaria"
        }
    },
    {
        "model": "Settings.PaymentMethod",
        "pk": 4,
        "fields": {
            "code": "PM",
            "description": "Pagos Moviles"
        }
    },
    {
        "model": "Settings.PaymentMethod",
        "pk": 5,
        "fields": {
            "code": "TBE",
            "description": "Transferencia Bancaria Electronica"
        }
    }
]